py_arrakis/__init__.py
py_arrakis/client.py
py_arrakis/sandbox.py
py_arrakis/sandbox_manager.py
py_arrakis-2.0.0.dist-info/LICENSE
py_arrakis-2.0.0.dist-info/METADATA
py_arrakis-2.0.0.dist-info/WHEEL
py_arrakis-2.0.0.dist-info/top_level.txt
py_arrakis-2.0.0.dist-info/RECORD
