Metadata-Version: 2.1
Name: py-arrakis
Version: 2.0.0
Summary: Python SDK for the Arrakis sandboxes - https://github.com/abshkbh/arrakis
Home-page: https://github.com/abshkbh/py-arrakis
Author: Abhishek Bhardwaj
Author-email: abshkbh@gmail.com
License: UNKNOWN
Keywords: virtualization,sandbox,vm,testing
Platform: UNKNOWN
Classifier: Development Status :: 3 - Alpha
Classifier: Programming Language :: Python :: 3
Classifier: Programming Language :: Python :: 3.9
Classifier: Programming Language :: Python :: 3.10
Classifier: Programming Language :: Python :: 3.11
Classifier: Programming Language :: Python :: 3.12
Classifier: License :: OSI Approved :: MIT License
Classifier: Operating System :: OS Independent
Classifier: Intended Audience :: Developers
Classifier: Topic :: Software Development :: Libraries :: Python Modules
Requires-Python: >=3.9
License-File: LICENSE
Requires-Dist: requests (>=2.25.0)
